{
  "timestamp": "2026-04-19T10:35:50.611364",
  "var_95": {
    "SPY": -1.6,
    "QQQ": -1.96,
    "IWM": -2.02,
    "TLT": -1.12,
    "GLD": -2.5
  },
  "var_99": {
    "SPY": -3.17,
    "QQQ": -3.69,
    "IWM": -3.33,
    "TLT": -1.89,
    "GLD": -4.38
  },
  "correlation_matrix": {
    "SPY": {
      "SPY": 1.0,
      "QQQ": 0.975,
      "IWM": 0.867,
      "TLT": 0.141,
      "GLD": 0.09
    },
    "QQQ": {
      "SPY": 0.975,
      "QQQ": 1.0,
      "IWM": 0.821,
      "TLT": 0.094,
      "GLD": 0.095
    },
    "IWM": {
      "SPY": 0.867,
      "QQQ": 0.821,
      "IWM": 1.0,
      "TLT": 0.156,
      "GLD": 0.123
    },
    "TLT": {
      "SPY": 0.141,
      "QQQ": 0.094,
      "IWM": 0.156,
      "TLT": 1.0,
      "GLD": 0.044
    },
    "GLD": {
      "SPY": 0.09,
      "QQQ": 0.095,
      "IWM": 0.123,
      "TLT": 0.044,
      "GLD": 1.0
    }
  },
  "max_drawdown": {
    "SPY": -13.72,
    "QQQ": -15.69,
    "IWM": -16.3,
    "TLT": -9.56,
    "GLD": -19.21
  },
  "sharpe_ratio": {
    "SPY": 1.21,
    "QQQ": 1.33,
    "IWM": 1.3,
    "TLT": -0.27,
    "GLD": 1.77
  },
  "portfolio_volatility": 14.49
}