{
  "timestamp": "2026-04-19T10:35:32.246371",
  "total_scanned": 88,
  "signals": [
    {
      "ticker": "SLB",
      "name": "SLB",
      "pattern": "VCP",
      "grade": "C",
      "stage": "Near",
      "stage_color": "#f59e0b",
      "signal_type": "APPROACHING",
      "score": 61,
      "market_regime": "SPY_SIDE",
      "mcap_tier": "C",
      "current_price": 52.66,
      "pivot": 54.8,
      "breakout_price": 55.9,
      "stop_loss": 42.24,
      "risk_reward": 0.99,
      "breakout_close_pct": -3.91,
      "distance_to_pivot_pct": 3.91,
      "c1": 65.6,
      "c2": 51.37,
      "c3": 25.83,
      "r12": 1.28,
      "r23": 1.99,
      "base_range_pct": 25.8,
      "rsi": 46.1,
      "atrp_pct": 3.52,
      "volume_ratio": 0.87,
      "above_ema50_ratio": 0.95,
      "ema_sep_pct": 14.16,
      "ema50": 49.36,
      "ema200": 43.24,
      "52w_high": 53.5,
      "52w_low": 31.72,
      "retest_depth_pct": 0.0,
      "retest_vol_ratio": 1.0,
      "vol_dryup_ratio": 1.24
    }
  ]
}